odoo9_addon_project_task_send_by_mail-9.0.1.0.0-py2.7-nspkg.pth
odoo9_addon_project_task_send_by_mail-9.0.1.0.0.dist-info/DESCRIPTION.rst
odoo9_addon_project_task_send_by_mail-9.0.1.0.0.dist-info/METADATA
odoo9_addon_project_task_send_by_mail-9.0.1.0.0.dist-info/RECORD
odoo9_addon_project_task_send_by_mail-9.0.1.0.0.dist-info/WHEEL
odoo9_addon_project_task_send_by_mail-9.0.1.0.0.dist-info/metadata.json
odoo9_addon_project_task_send_by_mail-9.0.1.0.0.dist-info/namespace_packages.txt
odoo9_addon_project_task_send_by_mail-9.0.1.0.0.dist-info/top_level.txt
odoo_addons/project_task_send_by_mail/README.rst
odoo_addons/project_task_send_by_mail/__init__.py
odoo_addons/project_task_send_by_mail/__openerp__.py
odoo_addons/project_task_send_by_mail/data/task_template.xml
odoo_addons/project_task_send_by_mail/i18n/es.po
odoo_addons/project_task_send_by_mail/models/__init__.py
odoo_addons/project_task_send_by_mail/models/project.py
odoo_addons/project_task_send_by_mail/static/description/icon.png
odoo_addons/project_task_send_by_mail/tests/__init__.py
odoo_addons/project_task_send_by_mail/tests/test_project_task_send_by_mail.py
odoo_addons/project_task_send_by_mail/views/project_task_views.xml
